nevu_ui/__init__.py
nevu_ui/animations/__init__.py
nevu_ui/animations/animation_base.py
nevu_ui/animations/animation_manager.py
nevu_ui/animations/animations_library.py
nevu_ui/color/__init__.py
nevu_ui/color/color.py
nevu_ui/color/color_theme.py
nevu_ui/color/color_theme_library.py
nevu_ui/core/__init__.py
nevu_ui/core/classes.py
nevu_ui/core/enums.py
nevu_ui/core/state.py
nevu_ui/fast/__init__.py
nevu_ui/fast/logic/__init__.py
nevu_ui/fast/logic/fast_logic.cp314t-win_amd64.pyd
nevu_ui/fast/logic/fast_logic.cpp
nevu_ui/fast/logic/fast_logic.pyi
nevu_ui/fast/nvvector2/__init__.py
nevu_ui/fast/nvvector2/nvvector2.cp314t-win_amd64.pyd
nevu_ui/fast/nvvector2/nvvector2.cpp
nevu_ui/fast/nvvector2/nvvector2.pyi
nevu_ui/fast/shapes/__init__.py
nevu_ui/fast/shapes/fast_shapes.cp314t-win_amd64.pyd
nevu_ui/fast/shapes/fast_shapes.cpp
nevu_ui/fast/shapes/fast_shapes.pyi
nevu_ui/fast/zsystem/__init__.py
nevu_ui/fast/zsystem/fast_zsystem.cp314t-win_amd64.pyd
nevu_ui/fast/zsystem/fast_zsystem.cpp
nevu_ui/fast/zsystem/fast_zsystem.pyi
nevu_ui/layouts/__init__.py
nevu_ui/layouts/checkbox_group.py
nevu_ui/layouts/column.py
nevu_ui/layouts/gallery_pages.py
nevu_ui/layouts/grid.py
nevu_ui/layouts/int_picker_grid.py
nevu_ui/layouts/layout_type.py
nevu_ui/layouts/pages.py
nevu_ui/layouts/row.py
nevu_ui/layouts/scrollable_base.py
nevu_ui/layouts/scrollable_column.py
nevu_ui/layouts/scrollable_row.py
nevu_ui/layouts/stack_base.py
nevu_ui/layouts/stack_column.py
nevu_ui/layouts/stack_row.py
nevu_ui/menu/__init__.py
nevu_ui/menu/menu.py
nevu_ui/nevuobj/__init__.py
nevu_ui/nevuobj/nevuobj.py
nevu_ui/nevusurface/__init__.py
nevu_ui/nevusurface/nevusurf.py
nevu_ui/rendering/__init__.py
nevu_ui/rendering/background_renderer.py
nevu_ui/rendering/background_renderergl.py
nevu_ui/rendering/blit.py
nevu_ui/rendering/dist_to_segment.py
nevu_ui/rendering/gradient.py
nevu_ui/rendering/shader.py
nevu_ui/size/__init__.py
nevu_ui/size/base.py
nevu_ui/size/rules.py
nevu_ui/size/units.py
nevu_ui-0.6.6.dist-info/licenses/LICENSE
nevu_ui-0.6.6.dist-info/METADATA
nevu_ui-0.6.6.dist-info/WHEEL
nevu_ui-0.6.6.dist-info/top_level.txt
nevu_ui-0.6.6.dist-info/RECORD
