Metadata-Version: 2.4
Name: nevu-ui
Version: 0.6.6
Summary: A powerful GUI framework for Pygame that allows you to create menus
Author-email: GolemNikidastrov <bebrovgolem@gmail.com>
Project-URL: Homepage, https://github.com/GolemBebrov/nevu-ui
Project-URL: Repository, https://github.com/GolemBebrov/nevu-ui
Classifier: Programming Language :: Python :: 3
Classifier: License :: OSI Approved :: MIT License
Classifier: Operating System :: OS Independent
Requires-Python: >=3.12
License-File: LICENSE
Requires-Dist: pygame-ce>=2.3.0
Requires-Dist: numpy
Requires-Dist: Pillow
Requires-Dist: moderngl
Dynamic: license-file
